{"standings":[{"team":"PBKS","p":9,"w":6,"l":2,"nr":1,"pts":13,"nrr":0.932},{"team":"RCB","p":9,"w":6,"l":3,"nr":0,"pts":12,"nrr":1.256},{"team":"RR","p":10,"w":6,"l":4,"nr":0,"pts":12,"nrr":0.45},{"team":"SRH","p":10,"w":6,"l":4,"nr":0,"pts":12,"nrr":0.427},{"team":"GT","p":10,"w":6,"l":4,"nr":0,"pts":12,"nrr":0.022},{"team":"CSK","p":9,"w":4,"l":5,"nr":0,"pts":8,"nrr":-0.015},{"team":"DC","p":9,"w":4,"l":5,"nr":0,"pts":8,"nrr":-0.789},{"team":"KKR","p":9,"w":2,"l":5,"nr":2,"pts":6,"nrr":-0.419},{"team":"LSG","p":8,"w":2,"l":5,"nr":1,"pts":5,"nrr":-0.931},{"team":"MI","p":9,"w":2,"l":7,"nr":0,"pts":4,"nrr":-1.017}],"team_results":{"SRH":[{"date":"2026-05-03","opponent":"KKR","venue":"\"Rajiv Gandhi International Stadium, Uppal, Hyderabad\"","result":"L","result_text":"KKR won by 7 wickets","margin":"by 7 wickets"},{"date":"2026-04-29","opponent":"MI","venue":"\"Wankhede Stadium, Mumbai\"","result":"W","result_text":"SRH won by 6 wickets","margin":"by 6 wickets"},{"date":"2026-04-25","opponent":"RR","venue":"\"Sawai Mansingh Stadium, Jaipur\"","result":"W","result_text":"SRH won by 5 wickets","margin":"by 5 wickets"},{"date":"2026-04-21","opponent":"DC","venue":"\"Rajiv Gandhi International Stadium, Uppal, Hyderabad\"","result":"W","result_text":"SRH won by 47 runs","margin":"by 47 runs"},{"date":"2026-04-18","opponent":"CSK","venue":"\"Rajiv Gandhi International Stadium, Uppal, Hyderabad\"","result":"W","result_text":"SRH won by 10 runs","margin":"by 10 runs"},{"date":"2026-04-13","opponent":"RR","venue":"\"Rajiv Gandhi International Stadium, Uppal, Hyderabad\"","result":"W","result_text":"SRH won by 57 runs","margin":"by 57 runs"},{"date":"2026-04-11","opponent":"PBKS","venue":"\"Maharaja Yadavindra Singh International Cricket Stadium, New Chandigarh\"","result":"L","result_text":"PBKS won by 6 wickets","margin":"by 6 wickets"},{"date":"2026-04-05","opponent":"LSG","venue":"\"Rajiv Gandhi International Stadium, Uppal, Hyderabad\"","result":"L","result_text":"LSG won by 5 wickets","margin":"by 5 wickets"},{"date":"2026-04-02","opponent":"KKR","venue":"\"Eden Gardens, Kolkata\"","result":"W","result_text":"SRH won by 65 runs","margin":"by 65 runs"},{"date":"2026-03-28","opponent":"RCB","venue":"\"M Chinnaswamy Stadium, Bengaluru\"","result":"L","result_text":"RCB won by 6 wickets","margin":"by 6 wickets"}],"RCB":[{"date":"2026-04-30","opponent":"GT","venue":"\"Narendra Modi Stadium, Ahmedabad\"","result":"L","result_text":"GT won by 4 wickets","margin":"by 4 wickets"},{"date":"2026-04-27","opponent":"DC","venue":"\"Arun Jaitley Stadium, Delhi\"","result":"W","result_text":"RCB won by 9 wickets","margin":"by 9 wickets"},{"date":"2026-04-24","opponent":"GT","venue":"\"M Chinnaswamy Stadium, Bengaluru\"","result":"W","result_text":"RCB won by 5 wickets","margin":"by 5 wickets"},{"date":"2026-04-18","opponent":"DC","venue":"\"M Chinnaswamy Stadium, Bengaluru\"","result":"L","result_text":"DC won by 6 wickets","margin":"by 6 wickets"},{"date":"2026-04-15","opponent":"LSG","venue":"\"M Chinnaswamy Stadium, Bengaluru\"","result":"W","result_text":"RCB won by 5 wickets","margin":"by 5 wickets"},{"date":"2026-04-12","opponent":"MI","venue":"\"Wankhede Stadium, Mumbai\"","result":"W","result_text":"RCB won by 18 runs","margin":"by 18 runs"},{"date":"2026-04-10","opponent":"RR","venue":"\"Barsapara Cricket Stadium, Guwahati\"","result":"L","result_text":"RR won by 6 wickets","margin":"by 6 wickets"},{"date":"2026-04-05","opponent":"CSK","venue":"\"M Chinnaswamy Stadium, Bengaluru\"","result":"W","result_text":"RCB won by 43 runs","margin":"by 43 runs"},{"date":"2026-03-28","opponent":"SRH","venue":"\"M Chinnaswamy Stadium, Bengaluru\"","result":"W","result_text":"RCB won by 6 wickets","margin":"by 6 wickets"}],"KKR":[{"date":"2026-05-03","opponent":"SRH","venue":"\"Rajiv Gandhi International Stadium, Uppal, Hyderabad\"","result":"W","result_text":"KKR won by 7 wickets","margin":"by 7 wickets"},{"date":"2026-04-26","opponent":"LSG","venue":"\"Bharat Ratna Shri Atal Bihari Vajpayee Ekana Cricket Stadium, Lucknow\"","result":"NR","result_text":"No result","margin":""},{"date":"2026-04-19","opponent":"RR","venue":"\"Eden Gardens, Kolkata\"","result":"W","result_text":"KKR won by 4 wickets","margin":"by 4 wickets"},{"date":"2026-04-17","opponent":"GT","venue":"\"Narendra Modi Stadium, Ahmedabad\"","result":"L","result_text":"GT won by 5 wickets","margin":"by 5 wickets"},{"date":"2026-04-14","opponent":"CSK","venue":"\"MA Chidambaram Stadium, Chepauk, Chennai\"","result":"L","result_text":"CSK won by 32 runs","margin":"by 32 runs"},{"date":"2026-04-09","opponent":"LSG","venue":"\"Eden Gardens, Kolkata\"","result":"L","result_text":"LSG won by 3 wickets","margin":"by 3 wickets"},{"date":"2026-04-06","opponent":"PBKS","venue":"\"Eden Gardens, Kolkata\"","result":"NR","result_text":"No result","margin":""},{"date":"2026-04-02","opponent":"SRH","venue":"\"Eden Gardens, Kolkata\"","result":"L","result_text":"SRH won by 65 runs","margin":"by 65 runs"},{"date":"2026-03-29","opponent":"MI","venue":"\"Wankhede Stadium, Mumbai\"","result":"L","result_text":"MI won by 6 wickets","margin":"by 6 wickets"}],"MI":[{"date":"2026-05-02","opponent":"CSK","venue":"\"MA Chidambaram Stadium, Chepauk, Chennai\"","result":"L","result_text":"CSK won by 8 wickets","margin":"by 8 wickets"},{"date":"2026-04-29","opponent":"SRH","venue":"\"Wankhede Stadium, Mumbai\"","result":"L","result_text":"SRH won by 6 wickets","margin":"by 6 wickets"},{"date":"2026-04-23","opponent":"CSK","venue":"\"Wankhede Stadium, Mumbai\"","result":"L","result_text":"CSK won by 103 runs","margin":"by 103 runs"},{"date":"2026-04-20","opponent":"GT","venue":"\"Narendra Modi Stadium, Ahmedabad\"","result":"W","result_text":"MI won by 99 runs","margin":"by 99 runs"},{"date":"2026-04-16","opponent":"PBKS","venue":"\"Wankhede Stadium, Mumbai\"","result":"L","result_text":"PBKS won by 7 wickets","margin":"by 7 wickets"},{"date":"2026-04-12","opponent":"RCB","venue":"\"Wankhede Stadium, Mumbai\"","result":"L","result_text":"RCB won by 18 runs","margin":"by 18 runs"},{"date":"2026-04-07","opponent":"RR","venue":"\"Barsapara Cricket Stadium, Guwahati\"","result":"L","result_text":"RR won by 27 runs","margin":"by 27 runs"},{"date":"2026-04-04","opponent":"DC","venue":"\"Arun Jaitley Stadium, Delhi\"","result":"L","result_text":"DC won by 6 wickets","margin":"by 6 wickets"},{"date":"2026-03-29","opponent":"KKR","venue":"\"Wankhede Stadium, Mumbai\"","result":"W","result_text":"MI won by 6 wickets","margin":"by 6 wickets"}],"CSK":[{"date":"2026-05-02","opponent":"MI","venue":"\"MA Chidambaram Stadium, Chepauk, Chennai\"","result":"W","result_text":"CSK won by 8 wickets","margin":"by 8 wickets"},{"date":"2026-04-26","opponent":"GT","venue":"\"MA Chidambaram Stadium, Chepauk, Chennai\"","result":"L","result_text":"GT won by 8 wickets","margin":"by 8 wickets"},{"date":"2026-04-23","opponent":"MI","venue":"\"Wankhede Stadium, Mumbai\"","result":"W","result_text":"CSK won by 103 runs","margin":"by 103 runs"},{"date":"2026-04-18","opponent":"SRH","venue":"\"Rajiv Gandhi International Stadium, Uppal, Hyderabad\"","result":"L","result_text":"SRH won by 10 runs","margin":"by 10 runs"},{"date":"2026-04-14","opponent":"KKR","venue":"\"MA Chidambaram Stadium, Chepauk, Chennai\"","result":"W","result_text":"CSK won by 32 runs","margin":"by 32 runs"},{"date":"2026-04-11","opponent":"DC","venue":"\"MA Chidambaram Stadium, Chepauk, Chennai\"","result":"W","result_text":"CSK won by 23 runs","margin":"by 23 runs"},{"date":"2026-04-05","opponent":"RCB","venue":"\"M Chinnaswamy Stadium, Bengaluru\"","result":"L","result_text":"RCB won by 43 runs","margin":"by 43 runs"},{"date":"2026-04-03","opponent":"PBKS","venue":"\"MA Chidambaram Stadium, Chepauk, Chennai\"","result":"L","result_text":"PBKS won by 5 wickets","margin":"by 5 wickets"},{"date":"2026-03-30","opponent":"RR","venue":"\"Barsapara Cricket Stadium, Guwahati\"","result":"L","result_text":"RR won by 8 wickets","margin":"by 8 wickets"}],"RR":[{"date":"2026-05-01","opponent":"DC","venue":"\"Sawai Mansingh Stadium, Jaipur\"","result":"L","result_text":"DC won by 7 wickets","margin":"by 7 wickets"},{"date":"2026-04-28","opponent":"PBKS","venue":"\"Maharaja Yadavindra Singh International Cricket Stadium, New Chandigarh\"","result":"W","result_text":"RR won by 6 wickets","margin":"by 6 wickets"},{"date":"2026-04-25","opponent":"SRH","venue":"\"Sawai Mansingh Stadium, Jaipur\"","result":"L","result_text":"SRH won by 5 wickets","margin":"by 5 wickets"},{"date":"2026-04-22","opponent":"LSG","venue":"\"Bharat Ratna Shri Atal Bihari Vajpayee Ekana Cricket Stadium, Lucknow\"","result":"W","result_text":"RR won by 40 runs","margin":"by 40 runs"},{"date":"2026-04-19","opponent":"KKR","venue":"\"Eden Gardens, Kolkata\"","result":"L","result_text":"KKR won by 4 wickets","margin":"by 4 wickets"},{"date":"2026-04-13","opponent":"SRH","venue":"\"Rajiv Gandhi International Stadium, Uppal, Hyderabad\"","result":"L","result_text":"SRH won by 57 runs","margin":"by 57 runs"},{"date":"2026-04-10","opponent":"RCB","venue":"\"Barsapara Cricket Stadium, Guwahati\"","result":"W","result_text":"RR won by 6 wickets","margin":"by 6 wickets"},{"date":"2026-04-07","opponent":"MI","venue":"\"Barsapara Cricket Stadium, Guwahati\"","result":"W","result_text":"RR won by 27 runs","margin":"by 27 runs"},{"date":"2026-04-04","opponent":"GT","venue":"\"Narendra Modi Stadium, Ahmedabad\"","result":"W","result_text":"RR won by 6 runs","margin":"by 6 runs"},{"date":"2026-03-30","opponent":"CSK","venue":"\"Barsapara Cricket Stadium, Guwahati\"","result":"W","result_text":"RR won by 8 wickets","margin":"by 8 wickets"}],"GT":[{"date":"2026-05-03","opponent":"PBKS","venue":"\"Narendra Modi Stadium, Ahmedabad\"","result":"W","result_text":"GT won by 4 wickets","margin":"by 4 wickets"},{"date":"2026-04-30","opponent":"RCB","venue":"\"Narendra Modi Stadium, Ahmedabad\"","result":"W","result_text":"GT won by 4 wickets","margin":"by 4 wickets"},{"date":"2026-04-26","opponent":"CSK","venue":"\"MA Chidambaram Stadium, Chepauk, Chennai\"","result":"W","result_text":"GT won by 8 wickets","margin":"by 8 wickets"},{"date":"2026-04-24","opponent":"RCB","venue":"\"M Chinnaswamy Stadium, Bengaluru\"","result":"L","result_text":"RCB won by 5 wickets","margin":"by 5 wickets"},{"date":"2026-04-20","opponent":"MI","venue":"\"Narendra Modi Stadium, Ahmedabad\"","result":"L","result_text":"MI won by 99 runs","margin":"by 99 runs"},{"date":"2026-04-17","opponent":"KKR","venue":"\"Narendra Modi Stadium, Ahmedabad\"","result":"W","result_text":"GT won by 5 wickets","margin":"by 5 wickets"},{"date":"2026-04-12","opponent":"LSG","venue":"\"Bharat Ratna Shri Atal Bihari Vajpayee Ekana Cricket Stadium, Lucknow\"","result":"W","result_text":"GT won by 7 wickets","margin":"by 7 wickets"},{"date":"2026-04-08","opponent":"DC","venue":"\"Arun Jaitley Stadium, Delhi\"","result":"W","result_text":"GT won by 1 runs","margin":"by 1 runs"},{"date":"2026-04-04","opponent":"RR","venue":"\"Narendra Modi Stadium, Ahmedabad\"","result":"L","result_text":"RR won by 6 runs","margin":"by 6 runs"},{"date":"2026-03-31","opponent":"PBKS","venue":"\"Maharaja Yadavindra Singh International Cricket Stadium, New Chandigarh\"","result":"L","result_text":"PBKS won by 3 wickets","margin":"by 3 wickets"}],"PBKS":[{"date":"2026-05-03","opponent":"GT","venue":"\"Narendra Modi Stadium, Ahmedabad\"","result":"L","result_text":"GT won by 4 wickets","margin":"by 4 wickets"},{"date":"2026-04-28","opponent":"RR","venue":"\"Maharaja Yadavindra Singh International Cricket Stadium, New Chandigarh\"","result":"L","result_text":"RR won by 6 wickets","margin":"by 6 wickets"},{"date":"2026-04-25","opponent":"DC","venue":"\"Arun Jaitley Stadium, Delhi\"","result":"W","result_text":"PBKS won by 6 wickets","margin":"by 6 wickets"},{"date":"2026-04-19","opponent":"LSG","venue":"\"Maharaja Yadavindra Singh International Cricket Stadium, New Chandigarh\"","result":"W","result_text":"PBKS won by 54 runs","margin":"by 54 runs"},{"date":"2026-04-16","opponent":"MI","venue":"\"Wankhede Stadium, Mumbai\"","result":"W","result_text":"PBKS won by 7 wickets","margin":"by 7 wickets"},{"date":"2026-04-11","opponent":"SRH","venue":"\"Maharaja Yadavindra Singh International Cricket Stadium, New Chandigarh\"","result":"W","result_text":"PBKS won by 6 wickets","margin":"by 6 wickets"},{"date":"2026-04-06","opponent":"KKR","venue":"\"Eden Gardens, Kolkata\"","result":"NR","result_text":"No result","margin":""},{"date":"2026-04-03","opponent":"CSK","venue":"\"MA Chidambaram Stadium, Chepauk, Chennai\"","result":"W","result_text":"PBKS won by 5 wickets","margin":"by 5 wickets"},{"date":"2026-03-31","opponent":"GT","venue":"\"Maharaja Yadavindra Singh International Cricket Stadium, New Chandigarh\"","result":"W","result_text":"PBKS won by 3 wickets","margin":"by 3 wickets"}],"LSG":[{"date":"2026-04-26","opponent":"KKR","venue":"\"Bharat Ratna Shri Atal Bihari Vajpayee Ekana Cricket Stadium, Lucknow\"","result":"NR","result_text":"No result","margin":""},{"date":"2026-04-22","opponent":"RR","venue":"\"Bharat Ratna Shri Atal Bihari Vajpayee Ekana Cricket Stadium, Lucknow\"","result":"L","result_text":"RR won by 40 runs","margin":"by 40 runs"},{"date":"2026-04-19","opponent":"PBKS","venue":"\"Maharaja Yadavindra Singh International Cricket Stadium, New Chandigarh\"","result":"L","result_text":"PBKS won by 54 runs","margin":"by 54 runs"},{"date":"2026-04-15","opponent":"RCB","venue":"\"M Chinnaswamy Stadium, Bengaluru\"","result":"L","result_text":"RCB won by 5 wickets","margin":"by 5 wickets"},{"date":"2026-04-12","opponent":"GT","venue":"\"Bharat Ratna Shri Atal Bihari Vajpayee Ekana Cricket Stadium, Lucknow\"","result":"L","result_text":"GT won by 7 wickets","margin":"by 7 wickets"},{"date":"2026-04-09","opponent":"KKR","venue":"\"Eden Gardens, Kolkata\"","result":"W","result_text":"LSG won by 3 wickets","margin":"by 3 wickets"},{"date":"2026-04-05","opponent":"SRH","venue":"\"Rajiv Gandhi International Stadium, Uppal, Hyderabad\"","result":"W","result_text":"LSG won by 5 wickets","margin":"by 5 wickets"},{"date":"2026-04-01","opponent":"DC","venue":"\"Bharat Ratna Shri Atal Bihari Vajpayee Ekana Cricket Stadium, Lucknow\"","result":"L","result_text":"DC won by 6 wickets","margin":"by 6 wickets"}],"DC":[{"date":"2026-05-01","opponent":"RR","venue":"\"Sawai Mansingh Stadium, Jaipur\"","result":"W","result_text":"DC won by 7 wickets","margin":"by 7 wickets"},{"date":"2026-04-27","opponent":"RCB","venue":"\"Arun Jaitley Stadium, Delhi\"","result":"L","result_text":"RCB won by 9 wickets","margin":"by 9 wickets"},{"date":"2026-04-25","opponent":"PBKS","venue":"\"Arun Jaitley Stadium, Delhi\"","result":"L","result_text":"PBKS won by 6 wickets","margin":"by 6 wickets"},{"date":"2026-04-21","opponent":"SRH","venue":"\"Rajiv Gandhi International Stadium, Uppal, Hyderabad\"","result":"L","result_text":"SRH won by 47 runs","margin":"by 47 runs"},{"date":"2026-04-18","opponent":"RCB","venue":"\"M Chinnaswamy Stadium, Bengaluru\"","result":"W","result_text":"DC won by 6 wickets","margin":"by 6 wickets"},{"date":"2026-04-11","opponent":"CSK","venue":"\"MA Chidambaram Stadium, Chepauk, Chennai\"","result":"L","result_text":"CSK won by 23 runs","margin":"by 23 runs"},{"date":"2026-04-08","opponent":"GT","venue":"\"Arun Jaitley Stadium, Delhi\"","result":"L","result_text":"GT won by 1 runs","margin":"by 1 runs"},{"date":"2026-04-04","opponent":"MI","venue":"\"Arun Jaitley Stadium, Delhi\"","result":"W","result_text":"DC won by 6 wickets","margin":"by 6 wickets"},{"date":"2026-04-01","opponent":"LSG","venue":"\"Bharat Ratna Shri Atal Bihari Vajpayee Ekana Cricket Stadium, Lucknow\"","result":"W","result_text":"DC won by 6 wickets","margin":"by 6 wickets"}]}}